<annotation>
    <folder>Renders2</folder>
    <filename>15-6y-7p.png</filename>
    <path>C:\Users\y_sta\Documents\CanBottleRecognition\Dataset\Renders2\15-6y-7p.png</path>
    <source>
        <database>Unknown</database>
    </source>
    <size>
        <width>600</width>
        <height>400</height>
        <depth>3</depth>
    </size>
    <segmented>0</segmented>
    <object>
        <name>bottle</name>
        <pose>Unspecified</pose>
        <truncated>0</truncated>
        <difficult>0</difficult>
        <bndbox>
            <xmin>269.6907138181402</xmin>
            <ymin>94.48760323438563</ymin>
            <xmax>357.1063671649243</xmax>
            <ymax>141.00773097953217</ymax>
        </bndbox>
    </object>    <object>
        <name>can</name>
        <pose>Unspecified</pose>
        <truncated>0</truncated>
        <difficult>0</difficult>
        <bndbox>
            <xmin>150.7733358720505</xmin>
            <ymin>97.82861862481931</ymin>
            <xmax>189.37047588930358</xmax>
            <ymax>122.23426914743789</ymax>
        </bndbox>
    </object>    <object>
        <name>can</name>
        <pose>Unspecified</pose>
        <truncated>0</truncated>
        <difficult>0</difficult>
        <bndbox>
            <xmin>590.4203389331134</xmin>
            <ymin>130.02276340751843</ymin>
            <xmax>600.0</xmax>
            <ymax>169.4058605996315</ymax>
        </bndbox>
    </object>
</annotation>
