<annotation>
    <folder>Renders1</folder>
    <filename>3-4y-5p.png</filename>
    <path>C:\Users\y_sta\Documents\CanBottleRecognition\Dataset\Renders1\3-4y-5p.png</path>
    <source>
        <database>Unknown</database>
    </source>
    <size>
        <width>600</width>
        <height>400</height>
        <depth>3</depth>
    </size>
    <segmented>0</segmented>
    <object>
        <name>bottle</name>
        <pose>Unspecified</pose>
        <truncated>0</truncated>
        <difficult>0</difficult>
        <bndbox>
            <xmin>106.00781248136904</xmin>
            <ymin>121.79297598851649</ymin>
            <xmax>191.82135567238956</xmax>
            <ymax>164.3002354108641</ymax>
        </bndbox>
    </object>    <object>
        <name>can</name>
        <pose>Unspecified</pose>
        <truncated>0</truncated>
        <difficult>0</difficult>
        <bndbox>
            <xmin>372.24351981652137</xmin>
            <ymin>144.0020105850166</ymin>
            <xmax>498.6516585829679</xmax>
            <ymax>223.11978830637278</ymax>
        </bndbox>
    </object>
</annotation>
