<annotation>
    <folder>Renders2</folder>
    <filename>0-7y-7p.png</filename>
    <path>C:\Users\y_sta\Documents\CanBottleRecognition\Dataset\Renders2\0-7y-7p.png</path>
    <source>
        <database>Unknown</database>
    </source>
    <size>
        <width>600</width>
        <height>400</height>
        <depth>3</depth>
    </size>
    <segmented>0</segmented>
    <object>
        <name>bottle</name>
        <pose>Unspecified</pose>
        <truncated>0</truncated>
        <difficult>0</difficult>
        <bndbox>
            <xmin>350.2830664877288</xmin>
            <ymin>96.28059853782283</ymin>
            <xmax>450.4272109603826</xmax>
            <ymax>160.35823735900593</ymax>
        </bndbox>
    </object>
</annotation>
