<annotation>
    <folder>Renders2</folder>
    <filename>1-4y-6p.png</filename>
    <path>C:\Users\y_sta\Documents\CanBottleRecognition\Dataset\Renders2\1-4y-6p.png</path>
    <source>
        <database>Unknown</database>
    </source>
    <size>
        <width>600</width>
        <height>400</height>
        <depth>3</depth>
    </size>
    <segmented>0</segmented>
    <object>
        <name>bottle</name>
        <pose>Unspecified</pose>
        <truncated>0</truncated>
        <difficult>0</difficult>
        <bndbox>
            <xmin>101.43522167080738</xmin>
            <ymin>121.23884101327049</ymin>
            <xmax>189.74878431999352</xmax>
            <ymax>161.94001502455913</ymax>
        </bndbox>
    </object>    <object>
        <name>can</name>
        <pose>Unspecified</pose>
        <truncated>0</truncated>
        <difficult>0</difficult>
        <bndbox>
            <xmin>262.90943360137464</xmin>
            <ymin>101.92577382073753</ymin>
            <xmax>298.30327798329415</xmax>
            <ymax>129.07461699304238</ymax>
        </bndbox>
    </object>
</annotation>
