<annotation>
    <folder>Renders2</folder>
    <filename>13-5y-4p.png</filename>
    <path>C:\Users\y_sta\Documents\CanBottleRecognition\Dataset\Renders2\13-5y-4p.png</path>
    <source>
        <database>Unknown</database>
    </source>
    <size>
        <width>600</width>
        <height>400</height>
        <depth>3</depth>
    </size>
    <segmented>0</segmented>
    <object>
        <name>bottle</name>
        <pose>Unspecified</pose>
        <truncated>0</truncated>
        <difficult>0</difficult>
        <bndbox>
            <xmin>191.31952387442567</xmin>
            <ymin>113.1119166739968</ymin>
            <xmax>273.7874690995407</xmax>
            <ymax>154.81262830070563</ymax>
        </bndbox>
    </object>    <object>
        <name>can</name>
        <pose>Unspecified</pose>
        <truncated>0</truncated>
        <difficult>0</difficult>
        <bndbox>
            <xmin>366.9050995912954</xmin>
            <ymin>117.16490278004845</ymin>
            <xmax>417.0874959277864</xmax>
            <ymax>142.14311698614867</ymax>
        </bndbox>
    </object>    <object>
        <name>can</name>
        <pose>Unspecified</pose>
        <truncated>0</truncated>
        <difficult>0</difficult>
        <bndbox>
            <xmin>376.48170017496426</xmin>
            <ymin>109.02082038191496</ymin>
            <xmax>408.6175163800509</xmax>
            <ymax>126.61127240280719</ymax>
        </bndbox>
    </object>
</annotation>
