<annotation>
    <folder>Renders2</folder>
    <filename>2-5y-9p.png</filename>
    <path>C:\Users\y_sta\Documents\CanBottleRecognition\Dataset\Renders2\2-5y-9p.png</path>
    <source>
        <database>Unknown</database>
    </source>
    <size>
        <width>600</width>
        <height>400</height>
        <depth>3</depth>
    </size>
    <segmented>0</segmented>
    <object>
        <name>bottle</name>
        <pose>Unspecified</pose>
        <truncated>0</truncated>
        <difficult>0</difficult>
        <bndbox>
            <xmin>184.86654368759685</xmin>
            <ymin>93.28826500777154</ymin>
            <xmax>272.7000516388094</xmax>
            <ymax>131.08913282032125</ymax>
        </bndbox>
    </object>    <object>
        <name>can</name>
        <pose>Unspecified</pose>
        <truncated>0</truncated>
        <difficult>0</difficult>
        <bndbox>
            <xmin>511.0205272424907</xmin>
            <ymin>84.51062035007185</ymin>
            <xmax>563.8394936988357</xmax>
            <ymax>110.21692947541104</ymax>
        </bndbox>
    </object>    <object>
        <name>can</name>
        <pose>Unspecified</pose>
        <truncated>0</truncated>
        <difficult>0</difficult>
        <bndbox>
            <xmin>134.72056575342805</xmin>
            <ymin>160.9017860994152</ymin>
            <xmax>231.62176514060528</xmax>
            <ymax>217.1834795138758</ymax>
        </bndbox>
    </object>
</annotation>
