<annotation>
    <folder>Training</folder>
    <filename>8-2y-7p.png</filename>
    <path>C:\Users\y_sta\Documents\CanBottleRecognition\Dataset\Training\8-2y-7p.png</path>
    <source>
        <database>Unknown</database>
    </source>
    <size>
        <width>600</width>
        <height>400</height>
        <depth>3</depth>
    </size>
    <segmented>0</segmented>
    <object>
        <name>Plastic Bottle</name>
        <pose>Unspecified</pose>
        <truncated>0</truncated>
        <difficult>0</difficult>
        <bndbox>
            <xmin>0.0</xmin>
            <ymin>238.23040904657447</ymin>
            <xmax>115.2132573039977</xmax>
            <ymax>326.49639705273205</ymax>
        </bndbox>
    </object>    <object>
        <name>Plastic Bottle</name>
        <pose>Unspecified</pose>
        <truncated>0</truncated>
        <difficult>0</difficult>
        <bndbox>
            <xmin>150.80308982470703</xmin>
            <ymin>85.61540125869836</ymin>
            <xmax>189.46261805596018</xmax>
            <ymax>107.54962136179103</ymax>
        </bndbox>
    </object>
</annotation>
